alphalens_modify/__init__.py
alphalens_modify/_version.py
alphalens_modify/performance.py
alphalens_modify/plotting.py
alphalens_modify/tears.py
alphalens_modify/utils.py
alphalens_modify/test_data/factor_data.csv
alphalens_modify/test_data/price_data.csv
alphalens_modify-0.1.0.dist-info/licenses/LICENSE
alphalens_modify-0.1.0.dist-info/METADATA
alphalens_modify-0.1.0.dist-info/WHEEL
alphalens_modify-0.1.0.dist-info/top_level.txt
alphalens_modify-0.1.0.dist-info/RECORD
