Metadata-Version: 2.4
Name: alphalens-modify
Version: 0.1.0
Summary: A modified version of alphalens with updated dependencies and fixes
Home-page: https://github.com/GenjiYin/alphalens-modify
Author: XiaoYinXu
Author-email: XiaoYinXu <965418170@qq.com>
Maintainer-email: XiaoYinXu <965418170@qq.com>
License: Apache-2.0
Project-URL: Homepage, https://github.com/GenjiYin/alphalens-modify
Project-URL: Documentation, https://github.com/GenjiYin/alphalens-modify
Project-URL: Repository, https://github.com/GenjiYin/alphalens-modify.git
Project-URL: Bug Tracker, https://github.com/GenjiYin/alphalens-modify/issues
Keywords: finance,quantitative,factor,analysis,investment
Classifier: Development Status :: 4 - Beta
Classifier: Intended Audience :: Financial and Insurance Industry
Classifier: Topic :: Office/Business :: Financial :: Investment
Classifier: License :: OSI Approved :: Apache Software License
Classifier: Programming Language :: Python :: 3
Classifier: Programming Language :: Python :: 3.12
Classifier: Programming Language :: Python :: 3.13
Requires-Python: >=3.12
License-File: LICENSE
Requires-Dist: pandas==2.2.3
Requires-Dist: numpy==1.26.4
Requires-Dist: scipy==1.14.1
Requires-Dist: statsmodels==0.14.5
Requires-Dist: matplotlib==3.9.2
Requires-Dist: seaborn==0.13.2
Requires-Dist: IPython
Provides-Extra: dev
Requires-Dist: pytest>=6.0; extra == "dev"
Requires-Dist: pytest-cov; extra == "dev"
Requires-Dist: black; extra == "dev"
Requires-Dist: flake8; extra == "dev"
Requires-Dist: mypy; extra == "dev"
Dynamic: author
Dynamic: home-page
Dynamic: license-file
